fastcountvectorizer/fastcountvectorizer.py
fastcountvectorizer/version.py
fastcountvectorizer/_ext.cpython-35m-i386-linux-gnu.so
fastcountvectorizer/_stopwords.py
fastcountvectorizer/__init__.py
fastcountvectorizer/compat.py
fastcountvectorizer/benchmark.py
fastcountvectorizer/tests/test_sklearn.py
fastcountvectorizer/tests/test_fastcountvectorizer.py
fastcountvectorizer/tests/__init__.py
fastcountvectorizer-0.1.0.dist-info/top_level.txt
fastcountvectorizer-0.1.0.dist-info/RECORD
fastcountvectorizer-0.1.0.dist-info/METADATA
fastcountvectorizer-0.1.0.dist-info/WHEEL
