Metadata-Version: 2.1
Name: fastcountvectorizer
Version: 0.1.0
Summary: A faster CountVectorizer alternative.
Home-page: https://github.com/smola/fastcountvectorizer
Author: Santiago M. Mola
Author-email: santi@mola.io
License: UNKNOWN
Keywords: sklearn scikit-learn nlp ngrams
Platform: UNKNOWN
Classifier: Development Status :: 3 - Alpha
Classifier: Intended Audience :: Developers
Classifier: Intended Audience :: Science/Research
Classifier: Programming Language :: Python
Classifier: Programming Language :: Python :: 3
Classifier: Programming Language :: Python :: 3.5
Classifier: Programming Language :: Python :: 3.6
Classifier: Programming Language :: Python :: 3.7
Classifier: Programming Language :: Python :: 3.8
Classifier: Programming Language :: Python :: 3 :: Only
Classifier: Programming Language :: Python :: Implementation :: CPython
Classifier: Operating System :: Microsoft :: Windows
Classifier: Operating System :: POSIX :: Linux
Classifier: Operating System :: MacOS :: MacOS X
Classifier: Topic :: Scientific/Engineering
Classifier: License :: OSI Approved :: MIT License
Requires-Python: >=3.5
Requires-Dist: scikit-learn
Requires-Dist: numpy
Requires-Dist: pybind11 (>=2.4)
